csf_kit/__init__.py
csf_kit/data/sample_news_file.txt
csf_kit/data/sample_senti_score.csv
csf_kit/data/stock_list_dates.csv
csf_kit/data/stock_price_data.csv
csf_kit/data/trade_calendar_zh.csv
csf_kit/news/__init__.py
csf_kit/news/util.py
csf_kit/news/sample_code/__init__.py
csf_kit/news/sample_code/sentimental_factor.py
csf_kit-0.1.4.3.dist-info/METADATA
csf_kit-0.1.4.3.dist-info/WHEEL
csf_kit-0.1.4.3.dist-info/top_level.txt
csf_kit-0.1.4.3.dist-info/RECORD
