Metadata-Version: 2.1
Name: csf-kit
Version: 0.1.4.3
Summary: StartKit for ChinaScope data
Home-page: https://pypi.org/project/csf-kit/
Author: ChinaScope
Author-email: song.lu@chinascope.com
License: UNKNOWN
Platform: UNKNOWN
Requires-Dist: pandas
Requires-Dist: numpy
Requires-Dist: zipfile37
Requires-Dist: python-dateutil
Requires-Dist: alphalens
